{
  "project_info": {
    "project_number": "917292570356",
    "project_id": "lvlapp-3a0e2",
    "storage_bucket": "lvlapp-3a0e2.appspot.com"
  },
  "client": [
    {
      "client_info": {
        "mobilesdk_app_id": "1:917292570356:android:75b8b641b78cdf674a30a1",
        "android_client_info": {
          "package_name": "com.aitu.lvlapp"
        }
      },
      "oauth_client": [
        {
          "client_id": "917292570356-3k7501lg6isrqe1ocrn8k5jmqvvats93.apps.googleusercontent.com",
          "client_type": 3
        }
      ],
      "api_key": [
        {
          "current_key": "AIzaSyDoBh3166AGyVR-As2d7SmCltD4_WMXM6s"
        }
      ],
      "services": {
        "appinvite_service": {
          "other_platform_oauth_client": [
            {
              "client_id": "917292570356-3k7501lg6isrqe1ocrn8k5jmqvvats93.apps.googleusercontent.com",
              "client_type": 3
            }
          ]
        }
      }
    }
  ],
  "configuration_version": "1"
}